odoo/addons/website_sale_payment_mode/README.rst
odoo/addons/website_sale_payment_mode/__init__.py
odoo/addons/website_sale_payment_mode/__manifest__.py
odoo/addons/website_sale_payment_mode/i18n/website_sale_payment_mode.pot
odoo/addons/website_sale_payment_mode/models/__init__.py
odoo/addons/website_sale_payment_mode/models/website.py
odoo/addons/website_sale_payment_mode/readme/CONTRIBUTORS.rst
odoo/addons/website_sale_payment_mode/readme/DESCRIPTION.rst
odoo/addons/website_sale_payment_mode/readme/INSTALL.rst
odoo/addons/website_sale_payment_mode/static/description/icon.png
odoo/addons/website_sale_payment_mode/static/description/index.html
odoo11_addon_website_sale_payment_mode-11.0.1.0.1.dist-info/METADATA
odoo11_addon_website_sale_payment_mode-11.0.1.0.1.dist-info/WHEEL
odoo11_addon_website_sale_payment_mode-11.0.1.0.1.dist-info/top_level.txt
odoo11_addon_website_sale_payment_mode-11.0.1.0.1.dist-info/RECORD
